setup.py
duybhsoft_custom_train/__init__.py
duybhsoft_custom_train/process_data.py
duybhsoft_custom_train/train.py
duybhsoft_custom_train/train_model.py
duybhsoft_custom_train/train_model_argparam.py
duybhsoft_custom_train/utils.py
duybhsoft_custom_train.egg-info/PKG-INFO
duybhsoft_custom_train.egg-info/SOURCES.txt
duybhsoft_custom_train.egg-info/dependency_links.txt
duybhsoft_custom_train.egg-info/requires.txt
duybhsoft_custom_train.egg-info/top_level.txt